firefw/__init__.py
firefw/core.py
firefw/irbuilder.py
firefw/runtime.py
firefw/tracing.py
firefw-1.4.3.dist-info/LICENSE.txt
firefw-1.4.3.dist-info/METADATA
firefw-1.4.3.dist-info/WHEEL
firefw-1.4.3.dist-info/RECORD
